py.typed
codat_banking/__init__.py
codat_banking/_hooks/__init__.py
codat_banking/_hooks/registration.py
codat_banking/_hooks/sdkhooks.py
codat_banking/_hooks/types.py
codat_banking/account_balances_sdk.py
codat_banking/accounts_sdk.py
codat_banking/basesdk.py
codat_banking/httpclient.py
codat_banking/models/__init__.py
codat_banking/models/account.py
codat_banking/models/accountbalance.py
codat_banking/models/accountbalanceamounts.py
codat_banking/models/accountbalances.py
codat_banking/models/accountidentifiers.py
codat_banking/models/accountidentifiertype.py
codat_banking/models/accountinstitution.py
codat_banking/models/accounts.py
codat_banking/models/accounttype.py
codat_banking/models/errormessage.py
codat_banking/models/errorvalidation.py
codat_banking/models/errorvalidationitem.py
codat_banking/models/get_accountop.py
codat_banking/models/get_transaction_categoryop.py
codat_banking/models/get_transactionop.py
codat_banking/models/halref.py
codat_banking/models/links.py
codat_banking/models/list_account_balancesop.py
codat_banking/models/list_accountsop.py
codat_banking/models/list_bank_transactionsop.py
codat_banking/models/list_transaction_categoriesop.py
codat_banking/models/list_transactionsop.py
codat_banking/models/sdkerror.py
codat_banking/models/security.py
codat_banking/models/transaction.py
codat_banking/models/transactioncategories.py
codat_banking/models/transactioncategory.py
codat_banking/models/transactioncategoryref.py
codat_banking/models/transactioncategorystatus.py
codat_banking/models/transactioncode.py
codat_banking/models/transactions.py
codat_banking/py.typed
codat_banking/sdk.py
codat_banking/sdkconfiguration.py
codat_banking/transaction_categories_sdk.py
codat_banking/transactions_sdk.py
codat_banking/types/__init__.py
codat_banking/types/basemodel.py
codat_banking/utils/__init__.py
codat_banking/utils/annotations.py
codat_banking/utils/enums.py
codat_banking/utils/eventstreaming.py
codat_banking/utils/forms.py
codat_banking-0.29.0.dist-info/METADATA
codat_banking-0.29.0.dist-info/WHEEL
codat_banking-0.29.0.dist-info/RECORD
